sagebox/__init__.py
sagebox/_pybox.cp312-win_amd64.pyd
sagebox-0.1.2.dist-info/METADATA
sagebox-0.1.2.dist-info/WHEEL
sagebox-0.1.2.dist-info/top_level.txt
sagebox-0.1.2.dist-info/RECORD
