Metadata-Version: 2.1
Name: sagebox
Version: 0.1.2
Summary: Sagebox Procedural GUI for Python
Author-email: Your Name <rob@sagebox.org>
License: MIT
Classifier: Programming Language :: Python :: 3
Classifier: Programming Language :: Python :: 3.7
Classifier: Programming Language :: Python :: 3.9
Classifier: Programming Language :: Python :: 3.10
Classifier: Programming Language :: Python :: 3.11
Classifier: Programming Language :: Python :: 3.12
Classifier: Operating System :: Microsoft :: Windows
Classifier: License :: OSI Approved :: MIT License
Requires-Python: <3.13,>=3.7
Requires-Dist: numpy
